dify_client/__init__.py
dify_client/client.py
dify_client-0.1.10.dist-info/LICENSE
dify_client-0.1.10.dist-info/METADATA
dify_client-0.1.10.dist-info/WHEEL
dify_client-0.1.10.dist-info/top_level.txt
dify_client-0.1.10.dist-info/RECORD
