Metadata-Version: 2.1
Name: dify-client
Version: 0.1.10
Summary: A package for interacting with the Dify Service-API
Home-page: https://github.com/langgenius/dify
Author: Dify
Author-email: hello@dify.ai
License: MIT
Keywords: dify nlp ai language-processing
Classifier: Programming Language :: Python :: 3
Classifier: License :: OSI Approved :: MIT License
Classifier: Operating System :: OS Independent
Requires-Python: >=3.6
License-File: LICENSE
Requires-Dist: requests
